openctp_ctp_channels/__about__.py
openctp_ctp_channels/__init__.py
openctp_ctp_channels/channels.py
openctp_ctp_channels/cli.py
openctp_ctp_channels-0.1.9.dist-info/METADATA
openctp_ctp_channels-0.1.9.dist-info/WHEEL
openctp_ctp_channels-0.1.9.dist-info/entry_points.txt
openctp_ctp_channels-0.1.9.dist-info/licenses/LICENSE
openctp_ctp_channels-0.1.9.dist-info/RECORD
