Metadata-Version: 2.4
Name: openctp-ctp-channels
Version: 0.1.9
Summary: Multi channels support for openctp-ctp
Project-URL: Documentation, https://github.com/Jedore/openctp-ctp-channels#readme
Project-URL: Issues, https://github.com/Jedore/openctp-ctp-channels/issues
Project-URL: Source, https://github.com/Jedore/openctp-ctp-channels
Author-email: Jedore <jedorefight@gmail.com>
License-Expression: BSD-3-Clause
License-File: LICENSE
Classifier: Programming Language :: Python
Classifier: Programming Language :: Python :: 3.7
Classifier: Programming Language :: Python :: 3.8
Classifier: Programming Language :: Python :: 3.9
Classifier: Programming Language :: Python :: 3.10
Classifier: Programming Language :: Python :: 3.11
Classifier: Programming Language :: Python :: 3.12
Classifier: Programming Language :: Python :: 3.13
Classifier: Programming Language :: Python :: 3.14
Classifier: Programming Language :: Python :: Implementation :: CPython
Requires-Python: >=3.7
Requires-Dist: click
Requires-Dist: openctp-ctp
Requires-Dist: requests
